oracledao.py
oracledao-0.1.2.dist-info/LICENSE.txt
oracledao-0.1.2.dist-info/METADATA
oracledao-0.1.2.dist-info/WHEEL
oracledao-0.1.2.dist-info/top_level.txt
oracledao-0.1.2.dist-info/RECORD
