Metadata-Version: 2.1
Name: oracledao
Version: 0.1.2
Summary: DAO Singleton module that encapsulate Oracle Database conection and simple methods
Home-page: UNKNOWN
Author: Ramon Campos
Author-email: r7campos@gmail.com
License: UNKNOWN
Keywords: oracle database conection cx-Oracle dao simple method
Platform: UNKNOWN
Classifier: Development Status :: 5 - Production/Stable
Classifier: Intended Audience :: Developers
Classifier: License :: OSI Approved :: MIT License
Classifier: Programming Language :: Python :: 3.5
Classifier: Programming Language :: Python :: 3.6
Classifier: Programming Language :: Python :: 3.7
Requires-Python: >=3
Requires-Dist: cx-Oracle
